scalingtheunet/__init__.py
scalingtheunet/data/__init__.py
scalingtheunet/data/get_dataset_HZG.py
scalingtheunet/data/prepared_dataset.py
scalingtheunet/data/split_dataset.py
scalingtheunet/datamodule/__init__.py
scalingtheunet/datamodule/hzg_mg_tomo.py
scalingtheunet/evaluation/__init__.py
scalingtheunet/executor/__init__.py
scalingtheunet/executor/inference.py
scalingtheunet/executor/testing.py
scalingtheunet/executor/training.py
scalingtheunet/models/__init__.py
scalingtheunet/models/simple_unet.py
scalingtheunet/utils/__init__.py
scalingtheunet/utils/file_system.py
scalingtheunet/utils/my_callback.py
scalingtheunet/utils/my_hydra.py
scalingtheunet/utils/my_losses.py
scalingtheunet/utils/my_metrics.py
scalingtheunet/utils/my_resolver.py
scalingtheunet/utils/stdlogging.py
scalingtheunet/utils/utils.py
scalingtheunet/visualization/__init__.py
scalingtheunet-0.1.0.dist-info/LICENSE
scalingtheunet-0.1.0.dist-info/WHEEL
scalingtheunet-0.1.0.dist-info/METADATA
scalingtheunet-0.1.0.dist-info/RECORD
