Metadata-Version: 2.1
Name: scalingtheunet
Version: 0.1.0
Summary: This project is the source code to our paper.
Author: Deutsches Elektronen-Synchrotron DESY
Author-email: ivo.baltruschat@desy.de
Requires-Python: >=3.9,<3.10
Classifier: Programming Language :: Python :: 3
Classifier: Programming Language :: Python :: 3.9
Requires-Dist: albumentations (>=1.0.3,<2.0.0)
Requires-Dist: connected-components-3d (>=3.2.1,<4.0.0)
Requires-Dist: dvc[all] (==2.9.5)
Requires-Dist: flatdict (>=4.0.1,<5.0.0)
Requires-Dist: grpcio (==1.43)
Requires-Dist: hydra-colorlog (>=1.1.0,<2.0.0)
Requires-Dist: hydra-core (>=1.1.1,<2.0.0)
Requires-Dist: hydra-optuna-sweeper (>=1.1.1,<2.0.0)
Requires-Dist: icecream (>=2.1.1,<3.0.0)
Requires-Dist: imagecodecs (>=2022.2.22,<2023.0.0)
Requires-Dist: ipywidgets (>=7.7.0,<8.0.0)
Requires-Dist: jupyterlab (>=3.2.9,<4.0.0)
Requires-Dist: mlflow (>=1.2,<2.0)
Requires-Dist: monai (>=0.7.0,<0.8.0)
Requires-Dist: mpire (>=2.3.3,<3.0.0)
Requires-Dist: natsort (>=7.1.1,<8.0.0)
Requires-Dist: numba (>=0.54.0,<0.55.0)
Requires-Dist: opencv-python (==4.5.1.48)
Requires-Dist: orderedattrdict (>=1.6.0,<2.0.0)
Requires-Dist: plotly (>=5.7.0,<6.0.0)
Requires-Dist: python-dotenv (>=0.19.2,<0.20.0)
Requires-Dist: ray (>=1.8,<2.0)
Requires-Dist: rich (>=10.12.0,<11.0.0)
Requires-Dist: scikit-image (>=0.17,<0.18)
Requires-Dist: scikit-learn (>=1.0,<2.0)
Requires-Dist: seaborn (>=0.11.2,<0.12.0)
Requires-Dist: seaborn-image (>=0.4.4,<0.5.0)
Requires-Dist: tensorflow (>=2.8,<2.9)
Requires-Dist: tqdm (>=4.62.2,<5.0.0)
Requires-Dist: wandb (>=0.12.7,<0.13.0)
